{
    "name": "Portero",
    "description": "",
    "dependencies": {
        "core": "*",
        "radio": "*",
        "microphone": "*",
        "pxt-rekabit": "github:cytrontechnologies/pxt-rekabit#v1.2.3",
        "pxt-sonar": "github:microsoft/pxt-sonar#v0.0.6"
    },
    "files": [
        "main.blocks",
        "main.ts",
        "README.md"
    ],
    "testFiles": [
        "test.ts"
    ],
    "targetVersions": {
        "target": "8.0.16",
        "targetId": "microbit"
    },
    "supportedTargets": [
        "microbit"
    ],
    "preferredEditor": "blocksprj"
}
